projectx_cli/__init__.py
projectx_cli/client.py
projectx_cli/config.py
projectx_cli/main.py
projectx_cli-0.1.0.dist-info/METADATA
projectx_cli-0.1.0.dist-info/WHEEL
projectx_cli-0.1.0.dist-info/entry_points.txt
projectx_cli-0.1.0.dist-info/RECORD
