Metadata-Version: 2.4
Name: projectx-cli
Version: 0.1.0
Summary: CLI for ProjectX - Smart notification bridge that monitors email and sends SMS alerts
Project-URL: Homepage, https://github.com/yourusername/projectx
Project-URL: Repository, https://github.com/yourusername/projectx
Author-email: Your Name <your@email.com>
License: MIT
Keywords: cli,digital-detox,email,notifications,productivity,sms
Classifier: Development Status :: 4 - Beta
Classifier: Environment :: Console
Classifier: Intended Audience :: Developers
Classifier: License :: OSI Approved :: MIT License
Classifier: Programming Language :: Python :: 3
Classifier: Programming Language :: Python :: 3.9
Classifier: Programming Language :: Python :: 3.10
Classifier: Programming Language :: Python :: 3.11
Classifier: Programming Language :: Python :: 3.12
Classifier: Topic :: Communications :: Email
Classifier: Topic :: Utilities
Requires-Python: >=3.9
Requires-Dist: httpx>=0.26.0
Requires-Dist: pydantic>=2.0.0
Requires-Dist: rich>=13.0.0
Requires-Dist: typer>=0.9.0
